ai_agent_mail_sender-0.2.2.dist-info/licenses/LICENSE
examples/__init__.py
examples/advanced_example.py
examples/ai_workflow_example.py
examples/basic_example.py
examples/enterprise_example.py
mail_sender/__init__.py
mail_sender/mailer.py
mail_sender/templates/basic_template.html
ai_agent_mail_sender-0.2.2.dist-info/METADATA
ai_agent_mail_sender-0.2.2.dist-info/WHEEL
ai_agent_mail_sender-0.2.2.dist-info/top_level.txt
ai_agent_mail_sender-0.2.2.dist-info/RECORD
