Metadata-Version: 2.4
Name: ai_agent_mail_sender
Version: 0.2.2
Summary: A secure and enterprise-grade email sender library for any workflow, including AI applications
Home-page: https://github.com/Brainstorm2605/email_sender
Author: MD ZAID ANWAR
Author-email: zaidanwar26@gmail.com
Keywords: email,workflow,ai,agent,mail,ai agent,llm
Classifier: Programming Language :: Python :: 3
Classifier: Programming Language :: Python :: 3.7
Classifier: Programming Language :: Python :: 3.8
Classifier: Programming Language :: Python :: 3.9
Classifier: Programming Language :: Python :: 3.10
Classifier: Programming Language :: Python :: 3.11
Classifier: License :: OSI Approved :: MIT License
Classifier: Operating System :: OS Independent
Classifier: Topic :: Communications :: Email
Classifier: Intended Audience :: Developers
Classifier: Intended Audience :: Information Technology
Classifier: Intended Audience :: System Administrators
Requires-Python: >=3.7
License-File: LICENSE
Requires-Dist: aiosmtplib>=2.0.0
Requires-Dist: jinja2>=3.0.0
Dynamic: author
Dynamic: author-email
Dynamic: classifier
Dynamic: description
Dynamic: description-content-type
Dynamic: home-page
Dynamic: keywords
Dynamic: license-file
Dynamic: requires-dist
Dynamic: requires-python
Dynamic: summary
